Metadata-Version: 1.1
Name: tensornumpykeras
Version: 0.0.1
Summary: My own test python project
Home-page: https://github.com/AlexKrudu/tensornumpykeras
Author: Alexandr Krudu
Author-email: KrudAlex@yandex.ru
License: BSD 2-clause
Platform: UNKNOWN
Classifier: Development Status :: 1 - Planning
Classifier: Intended Audience :: Science/Research
Classifier: License :: OSI Approved :: BSD License
Classifier: Operating System :: POSIX :: Linux
Classifier: Programming Language :: Python :: 3
